orbit_cpu/__init__.py
orbit_cpu/orbit.py
orbit_cpu/utils.py
orbit_cpu-0.1.9.dist-info/METADATA
orbit_cpu-0.1.9.dist-info/WHEEL
orbit_cpu-0.1.9.dist-info/top_level.txt
orbit_cpu-0.1.9.dist-info/RECORD
